dbt/adapters/ocean_spark/__init__.py
dbt/adapters/ocean_spark/__version__.py
dbt/adapters/ocean_spark/column.py
dbt/adapters/ocean_spark/connections.py
dbt/adapters/ocean_spark/impl.py
dbt/adapters/ocean_spark/python_submissions.py
dbt/adapters/ocean_spark/relation.py
dbt/adapters/ocean_spark/session.py
dbt/adapters/ocean_spark/twebsocket.py
dbt/include/ocean_spark/__init__.py
dbt/include/ocean_spark/dbt_project.yml
dbt/include/ocean_spark/profile_template.yml
dbt/include/ocean_spark/macros/adapters.sql
dbt/include/ocean_spark/macros/apply_grants.sql
dbt/include/ocean_spark/macros/materializations/clone.sql
dbt/include/ocean_spark/macros/materializations/seed.sql
dbt/include/ocean_spark/macros/materializations/snapshot.sql
dbt/include/ocean_spark/macros/materializations/table.sql
dbt/include/ocean_spark/macros/materializations/view.sql
dbt/include/ocean_spark/macros/materializations/incremental/column_helpers.sql
dbt/include/ocean_spark/macros/materializations/incremental/incremental.sql
dbt/include/ocean_spark/macros/materializations/incremental/strategies.sql
dbt/include/ocean_spark/macros/materializations/incremental/validate.sql
dbt/include/ocean_spark/macros/utils/any_value.sql
dbt/include/ocean_spark/macros/utils/array_append.sql
dbt/include/ocean_spark/macros/utils/array_concat.sql
dbt/include/ocean_spark/macros/utils/array_construct.sql
dbt/include/ocean_spark/macros/utils/assert_not_null.sql
dbt/include/ocean_spark/macros/utils/bool_or.sql
dbt/include/ocean_spark/macros/utils/concat.sql
dbt/include/ocean_spark/macros/utils/dateadd.sql
dbt/include/ocean_spark/macros/utils/datediff.sql
dbt/include/ocean_spark/macros/utils/escape_single_quotes.sql
dbt/include/ocean_spark/macros/utils/listagg.sql
dbt/include/ocean_spark/macros/utils/split_part.sql
dbt/include/ocean_spark/macros/utils/timestamps.sql
dbt_ocean_spark-1.6.2.dist-info/METADATA
dbt_ocean_spark-1.6.2.dist-info/WHEEL
dbt_ocean_spark-1.6.2.dist-info/top_level.txt
dbt_ocean_spark-1.6.2.dist-info/RECORD
