Metadata-Version: 2.1
Name: dbt-ocean-spark
Version: 1.6.2
Summary: The Apache Spark adapter plugin for dbt
Home-page: https://github.com/sigmarkarl/dbt-ocean-spark
Author: dbt Labs
Author-email: info@dbtlabs.com
Classifier: Development Status :: 5 - Production/Stable
Classifier: License :: OSI Approved :: Apache Software License
Classifier: Operating System :: Microsoft :: Windows
Classifier: Operating System :: MacOS :: MacOS X
Classifier: Operating System :: POSIX :: Linux
Classifier: Programming Language :: Python :: 3.8
Classifier: Programming Language :: Python :: 3.9
Classifier: Programming Language :: Python :: 3.10
Requires-Python: >=3.8
Requires-Dist: dbt-core ~=1.6.0
Requires-Dist: sqlparams >=3.0.0
Provides-Extra: odbc
Requires-Dist: pyodbc ~=4.0.30 ; extra == 'odbc'
Provides-Extra: pyhive
Requires-Dist: PyHive[hive] <0.7.0,>=0.6.0 ; extra == 'pyhive'
Requires-Dist: thrift <0.17.0,>=0.11.0 ; extra == 'pyhive'
Provides-Extra: all
Requires-Dist: pyodbc ~=4.0.30 ; extra == 'all'
Requires-Dist: PyHive[hive] <0.7.0,>=0.6.0 ; extra == 'all'
Requires-Dist: thrift <0.17.0,>=0.11.0 ; extra == 'all'
Requires-Dist: pyspark <4.0.0,>=3.0.0 ; extra == 'all'
Provides-Extra: session
Requires-Dist: pyspark <4.0.0,>=3.0.0 ; extra == 'session'
